pywaterkotte/__init__.py
pywaterkotte/detect.py
pywaterkotte/easycon.py
pywaterkotte/ecotouch.py
pywaterkotte/test.py
pywaterkotte/test_easycon.py
pywaterkotte/test_ecotouch.py
pywaterkotte2-0.0.14.dist-info/LICENSE
pywaterkotte2-0.0.14.dist-info/METADATA
pywaterkotte2-0.0.14.dist-info/WHEEL
pywaterkotte2-0.0.14.dist-info/top_level.txt
pywaterkotte2-0.0.14.dist-info/RECORD
