Metadata-Version: 2.1
Name: pywaterkotte2
Version: 0.0.14
Summary: python library for waterkotte heatpumps
Home-page: https://github.com/pattisonmichael/pywaterkotte
Author: Michael Pattison
Author-email: michael@pattison.de
Classifier: Programming Language :: Python :: 3
Classifier: License :: OSI Approved :: MIT License
Classifier: Operating System :: OS Independent
Requires-Python: >=3.8
License-File: LICENSE
